README.txt
setup.py
src/epostkr/__init__.py
src/epostkr.egg-info/PKG-INFO
src/epostkr.egg-info/SOURCES.txt
src/epostkr.egg-info/dependency_links.txt
src/epostkr.egg-info/entry_points.txt
src/epostkr.egg-info/top_level.txt