Metadata-Version: 1.0
Name: epostkr
Version: 0.1
Summary: a client for epost.kr OpenAPI
Home-page: https://github.com/mete0r/epostkr
Author: mete0r
Author-email: mete0r@sarangbang.or.kr
License: GNU Affero GPL v3
Platform: UNKNOWN
Classifier: Development Status :: 1 - Planning
Classifier: Environment :: Console
Classifier: Intended Audience :: Developers
Classifier: Intended Audience :: End Users/Desktop
Classifier: License :: OSI Approved :: GNU Affero General Public License v3
Classifier: Natural Language :: English
Classifier: Natural Language :: Korean
Classifier: Programming Language :: Python
Classifier: Topic :: Internet
Classifier: Topic :: Software Development :: Libraries :: Python Modules
Classifier: Topic :: Utilities
